{
  "badges": [],
  "created_at": "2017-07-02T18:26:22.246000",
  "deleted": null,
  "description": "Ce jeu de donn\u00e9es d\u00e9taille le trafic des entrants directs sur le r\u00e9seau ferr\u00e9 RATP en 2016.\n\nLes \u00ab entrants directs \u00bb sont exclusivement les voyageurs provenant de la voie publique ou du r\u00e9seau SNCF entrant sur le r\u00e9seau de transport RATP en validant un titre de transport valide.\n\nLes voyageurs en correspondance (y compris correspondances m\u00e9tro/RER) sur le r\u00e9seau RATP ne sont pas comptabilis\u00e9s.",
  "extras": {
    "harvest:domain": "data.iledefrance.fr",
    "harvest:last_update": "2017-11-27T06:03:32.110100",
    "harvest:remote_id": "trafic-annuel-entrant-par-station-du-reseau-ferre-2016",
    "harvest:source_id": "5898eb3ec751df390fae0a65",
    "ods:has_records": true,
    "ods:url": "https://data.iledefrance.fr//explore/dataset/trafic-annuel-entrant-par-station-du-reseau-ferre-2016/"
  },
  "frequency": "unknown",
  "frequency_date": null,
  "id": "59591eaea3a7291dcf9c8186",
  "last_modified": "2017-11-27T06:03:32.112000",
  "last_update": "2017-11-27T06:03:32.109000",
  "license": "fr-lo",
  "metrics": {
    "discussions": 0,
    "followers": 0,
    "issues": 0,
    "nb_hits": 0,
    "nb_uniq_visitors": 0,
    "nb_visits": 0,
    "reuses": 0,
    "views": 0
  },
  "organization": {
    "acronym": null,
    "class": "Organization",
    "id": "534fffa8a3a7292c64a780c8",
    "logo": "https://www.data.gouv.fr/s/avatars/2015-03-05/a6cd667d87434dce8ed85084db889359/LOGO-IDF-SIGNATURE-CAMPAGNE-original.jpg",
    "logo_thumbnail": "https://www.data.gouv.fr/s/avatars/2015-03-05/a6cd667d87434dce8ed85084db889359/LOGO-IDF-SIGNATURE-CAMPAGNE-100.jpg",
    "name": "R\u00e9gion \u00cele-de-France",
    "page": "https://www.data.gouv.fr/fr/organizations/region-ile-de-france/",
    "slug": "region-ile-de-france",
    "uri": "https://www.data.gouv.fr/api/1/organizations/region-ile-de-france/"
  },
  "owner": null,
  "page": "https://www.data.gouv.fr/fr/datasets/trafic-annuel-entrant-par-station-du-reseau-ferre-2016/",
  "private": false,
  "resources": [
    {
      "checksum": null,
      "created_at": "2017-11-27T06:03:32.109000",
      "description": "- *Rang*: rang[int]\n- *R\u00e9seau*: reseau[text]\n- *Station*: station[text]\n- *Trafic*: trafic[int]\n- *Correspondance_1*: correspondance_1[text]\n- *Correspondance_2*: correspondance_2[text]\n- *Correspondance_3*: correspondance_3[text]\n- *Correspondance_4*: correspondance_4[text]\n- *Correspondance_5*: correspondance_5[text]\n- *Ville*: ville[text]\n- *Arrondissement pour Paris*: arrondissement_pour_paris[int]\n- *Column 12*: column_12[text]\n- *Column 13*: column_13[text]\n- *Column 14*: column_14[text]\n- *Column 15*: column_15[text]\n",
      "extras": {},
      "filesize": null,
      "filetype": "remote",
      "format": "csv",
      "id": "e653d253-b818-43ff-94b9-94fdfc25beb4",
      "last_modified": "2017-05-15T16:06:13",
      "latest": "https://www.data.gouv.fr/fr/datasets/r/e653d253-b818-43ff-94b9-94fdfc25beb4",
      "metrics": {
        "nb_hits": 0,
        "nb_uniq_visitors": 0,
        "nb_visits": 0,
        "views": 0
      },
      "mime": "text/csv",
      "published": "2017-11-27T06:03:32.109000",
      "title": "Export au format CSV",
      "url": "https://data.iledefrance.fr//explore/dataset/trafic-annuel-entrant-par-station-du-reseau-ferre-2016/download?format=csv&timezone=Europe/Berlin&use_labels_for_header=true"
    },
    {
      "checksum": null,
      "created_at": "2017-11-27T06:03:32.109000",
      "description": "- *Rang*: rang[int]\n- *R\u00e9seau*: reseau[text]\n- *Station*: station[text]\n- *Trafic*: trafic[int]\n- *Correspondance_1*: correspondance_1[text]\n- *Correspondance_2*: correspondance_2[text]\n- *Correspondance_3*: correspondance_3[text]\n- *Correspondance_4*: correspondance_4[text]\n- *Correspondance_5*: correspondance_5[text]\n- *Ville*: ville[text]\n- *Arrondissement pour Paris*: arrondissement_pour_paris[int]\n- *Column 12*: column_12[text]\n- *Column 13*: column_13[text]\n- *Column 14*: column_14[text]\n- *Column 15*: column_15[text]\n",
      "extras": {},
      "filesize": null,
      "filetype": "remote",
      "format": "json",
      "id": "3c05b44e-40cc-4761-93f8-dfa3f5d8ac5d",
      "last_modified": "2017-05-15T16:06:13",
      "latest": "https://www.data.gouv.fr/fr/datasets/r/3c05b44e-40cc-4761-93f8-dfa3f5d8ac5d",
      "metrics": {
        "nb_hits": 0,
        "nb_uniq_visitors": 0,
        "nb_visits": 0,
        "views": 0
      },
      "mime": "application/json",
      "published": "2017-11-27T06:03:32.109000",
      "title": "Export au format JSON",
      "url": "https://data.iledefrance.fr//explore/dataset/trafic-annuel-entrant-par-station-du-reseau-ferre-2016/download?format=json&timezone=Europe/Berlin&use_labels_for_header=true"
    }
  ],
  "slug": "trafic-annuel-entrant-par-station-du-reseau-ferre-2016",
  "spatial": null,
  "tags": [
    "deplacements-transports",
    "metro",
    "rer",
    "titre-de-transport",
    "trafic",
    "transports-en-commun",
    "voyageurs"
  ],
  "temporal_coverage": null,
  "title": "Trafic annuel entrant par station du r\u00e9seau ferr\u00e9 2016",
  "uri": "https://www.data.gouv.fr/api/1/datasets/trafic-annuel-entrant-par-station-du-reseau-ferre-2016/"
}